verysimplemodulebyNaren/__init__.py
verysimplemodulebyNaren/test.py
verysimplemodulebyNaren-0.0.4.dist-info/LICENSE.txt
verysimplemodulebyNaren-0.0.4.dist-info/METADATA
verysimplemodulebyNaren-0.0.4.dist-info/WHEEL
verysimplemodulebyNaren-0.0.4.dist-info/top_level.txt
verysimplemodulebyNaren-0.0.4.dist-info/RECORD
