Metadata-Version: 2.1
Name: verysimplemodulebyNaren
Version: 0.0.4
Summary: My first Python package
Home-page: UNKNOWN
Author: Naren Dawar
Author-email: UNKNOWN
License: UNKNOWN
Keywords: python,first package
Platform: UNKNOWN
Classifier: Intended Audience :: Education
Classifier: Programming Language :: Python :: 2
Classifier: Programming Language :: Python :: 3
Classifier: Operating System :: MacOS :: MacOS X
Classifier: Operating System :: Microsoft :: Windows
